{"data":{"BNTBTC":0.9253676906,"PPTBTC":0.8916533713,"EVXBTC":0.8832661532,"EDOBTC":0.8781833557,"GXSBTC":0.8740168904,"OAXBTC":0.8634895384,"WINGSBTC":0.83416958,"RLCBTC":0.7913855943,"HCBTC":0.7866414373,"BNTETH":0.781285636,"VIABTC":0.7745363472,"EVXETH":0.7607292254,"ELFBTC":0.728533637,"XRPBTC":0.6908708989,"GRSBTC":0.6657870188,"NULSBTC":0.6520213592,"ADXBTC":0.6498150095,"BQXBTC":0.6494077869,"NULSUSDT":0.632177064,"THETABTC":0.6240297884,"BRDBTC":0.6112656761,"VIBEBTC":0.5989241914,"MDABTC":0.5943910086,"XRPETH":0.5936380915,"ARNBTC":0.592972925,"CLOAKBTC":0.5926983848,"PHXETH":0.5729251,"XRPUSDT":0.5590079222,"XZCBTC":0.5544926704,"SUBBTC":0.5481204484,"NASBTC":0.528752321,"PIVXBTC":0.5284612993,"NPXSETH":0.5233851218,"ONTBTC":0.5198099525,"ARKBTC":0.5123918401,"DGDBTC":0.5037420897,"LUNBTC":0.478724697,"OAXETH":0.4657541111,"GVTBTC":0.4229381606,"INSBTC":0.418112718,"THETAETH":0.4173633024,"XRPTUSD":0.4139644335,"HOTETH":0.4082651932,"XLMTUSD":0.4072002924,"XRPPAX":0.4032834337,"AGIBTC":0.398409257,"NXSBTC":0.3349149723,"MFTETH":0.3338130236,"WAVESBTC":0.3321762736,"XLMETH":0.3158974016,"ONTUSDT":0.3155549049,"SALTBTC":0.3135176899,"ZENBTC":0.3125122348,"GTOBTC":0.3115983008,"XLMBTC":0.3115741167,"AMBBTC":0.3046433487,"MTLBTC":0.3031353324,"MODBTC":0.3001702719,"NANOBTC":0.2998956588,"ADATUSD":0.2868636487,"ONTETH":0.2736671815,"KMDBTC":0.2711859888,"ARNETH":0.2680245628,"TRXUSDC":0.2533983666,"WAVESETH":0.2481710516,"TUSDETH":0.2438494351,"WAVESBNB":0.2174561409,"DLTETH":0.2174113827,"EOSUSDC":0.2141346935,"XLMUSDT":0.212595004,"XLMPAX":0.2078613619,"NANOETH":0.2047267716,"WAVESUSDT":0.1997930822,"DLTBTC":0.1863073089,"GTOETH":0.1826031263,"TUSDUSDT":0.1723754312,"SKYBTC":0.1477648853,"TRXETH":0.1467825948,"BCHABCTUSD":0.140940459,"XLMUSDC":0.1402774694,"XRPUSDC":0.1368542966,"XMRBTC":0.134120823,"WAVESTUSD":0.1330661079,"ZILETH":0.1323274049,"USDCUSDT":0.1291640455,"BCDBTC":0.1234394662,"GASBTC":0.1194083294,"BNBPAX":0.1160585536,"TRXXRP":0.105832011,"REPBTC":0.10297495,"BNBETH":0.1000837342,"WANBTC":0.0962545467,"BCHABCBTC":0.0919823763,"LTCETH":0.091752512,"RDNBTC":0.0809395298,"TUSDBTC":0.0785942581,"XRPBNB":0.0774520126,"ZECBTC":0.0746627877,"WTCBTC":0.0665048961,"IOTAUSDT":0.0632561416,"TRXTUSD":0.0564414685,"BCHABCUSDT":0.0559647935,"XLMBNB":0.0494187729,"WABIBTC":0.0493703715,"USDCPAX":0.0416459962,"NEOTUSD":0.0397570207,"LTCBTC":0.0386402739,"LRCBTC":0.020725574,"TRXUSDT":0.0014696204,"MITHBTC":-0.0028297131,"ZRXETH":-0.0122412266,"PAXUSDT":-0.0150083553,"BNBUSDC":-0.0186531125,"APPCBTC":-0.0236974023,"ADAETH":-0.0336559907,"REPETH":-0.0394441447,"LOOMBTC":-0.0409087577,"BTCPAX":-0.046677165,"NEOETH":-0.0555789738,"ADABNB":-0.0702385498,"ZRXBTC":-0.0876523663,"BNBUSDT":-0.100608142,"EOSETH":-0.1047595469,"LTCUSDT":-0.1052322657,"BNBBTC":-0.1124275045,"LSKBTC":-0.1132780504,"DASHBTC":-0.1161495324,"ETHPAX":-0.1201013201,"LINKETH":-0.1266898449,"BTGBTC":-0.128318946,"NEOBTC":-0.1296256055,"BCHSVBTC":-0.1316594184,"TRXBNB":-0.1475533128,"USDCTUSD":-0.1498396191,"KNCBTC":-0.1535256503,"BTCUSDC":-0.1542854027,"BATETH":-0.1559811109,"ETCUSDT":-0.1905905714,"TUSDBNB":-0.1932669887,"ETHBTC":-0.1933845634,"LINKTUSD":-0.1945563434,"ADAUSDT":-0.195742341,"LINKBTC":-0.2081090047,"BTCUSDT":-0.2119009308,"LTCBNB":-0.2125801029,"ENGBTC":-0.213864433,"BCHSVUSDT":-0.2190127983,"LTCTUSD":-0.2234824896,"NEOUSDT":-0.2307050439,"LRCETH":-0.2390610686,"QTUMBTC":-0.2459857965,"BATBTC":-0.2474206555,"ETHUSDT":-0.2485305691,"POWRBTC":-0.2497091335,"QTUMUSDT":-0.2501612818,"LINKUSDT":-0.2746829508,"ETHUSDC":-0.2805452916,"ICXETH":-0.2805847464,"MCOBTC":-0.2927518053,"VETUSDT":-0.2939722716,"POLYBTC":-0.3021140351,"EOSBNB":-0.3052283374,"EOSBTC":-0.3060276529,"AEBTC":-0.3192784096,"IOTABTC":-0.3238731815,"ETCBTC":-0.3245897482,"NEBLBTC":-0.3399555255,"EOSUSDT":-0.3505023923,"IOTAETH":-0.352467937,"ICXUSDT":-0.3709682248,"EOSPAX":-0.3735283387,"LINKUSDC":-0.3771790311,"DCRBTC":-0.3802397818,"STRATBTC":-0.4047945984,"ICXBTC":-0.4348172775,"FUNETH":-0.4353947671,"XEMBTC":-0.4367045297,"PAXTUSD":-0.4838984128,"STEEMBTC":-0.4888563701,"AIONBTC":-0.5624082273,"NAVBTC":-0.6236380997,"OMGETH":-0.6687539725,"OMGBTC":-0.7319185789},"startDate":"2019-01-25","endDate":"2019-02-01","numDays":7,"excludedPairs":["ETCETH","REPBNB","PIVXBNB","ADXETH","HCETH","DNTBTC","BTSBTC","VIAETH","MITHBNB","BQXETH","WPRBTC","BTTBTC","BLZETH","QSPETH","SALTETH","BTTBNB","HOTBTC","ENJBTC","POEETH","STEEMETH","YOYOETH","QTUMBNB","ADABTC","MTHETH","VIABNB","NULSETH","ETCBNB","SUBETH","BCHSVPAX","NCASHETH","GVTETH","NEBLETH","IOTXETH","EDOETH","VETBTC","VENETH","CHATBTC","LTCPAX","CDTETH","MODETH","POWRETH","KNCETH","QKCBTC","DATAETH","WANETH","THETABNB","APPCBNB","STEEMBNB","WAVESPAX","BCHSVTUSD","DLTBNB","TNBETH","FUELETH","NASETH","MANABTC","RCNETH","GNTBNB","VIBEETH","AMBETH","AIONBNB","CNDETH","POABNB","RLCBNB","RENBNB","NPXSBTC","BCDETH","QTUMETH","NCASHBNB","GOBTC","GNTBTC","MTHBTC","INSETH","TNTETH","BCPTBTC","NANOBNB","POABTC","ARKETH","WINGSETH","LENDETH","QLCBNB","HSRETH","DATABTC","PAXETH","GOBNB","CNDBNB","NULSBNB","ARDRETH","FUELBTC","GRSETH","GTOBNB","MCOETH","XEMETH","RPXBTC","BTGETH","USDCBTC","RCNBNB","LOOMBNB","BCNETH","POLYBNB","TRIGETH","MFTBNB","TRIGBNB","EOSTUSD","DGDETH","CNDBTC","VENBTC","ENJETH","CVCBTC","BTTUSDT","BCCBTC","AEBNB","ZENBNB","AIONETH","RPXBNB","RVNBTC","ONTBNB","CMTBTC","XZCETH","NXSBNB","SNMBTC","KEYBTC","WAVESUSDC","LENDBTC","BCHSVUSDC","XEMBNB","SYSBNB","PHXBNB","LSKETH","QKCETH","MDAETH","SNTBTC","SCBNB","ARDRBNB","MTLETH","POAETH","ICNBTC","ASTETH","REQBTC","VIBETH","BLZBTC","QSPBNB","AEETH","QLCETH","SNMETH","LUNETH","DENTETH","XVGBTC","WABIETH","ZILBTC","GNTETH","FUNBTC","BLZBNB","SCBTC","NEBLBNB","TRIGBTC","STORJBTC","VIBBTC","TRXBTC","GXSETH","NXSETH","SKYETH","VENUSDT","RVNBNB","SNTETH","DASHETH","CVCETH","BTSBNB","DENTBTC","POEBTC","RCNBTC","MFTBTC","POWRBNB","SNGLSETH","NAVETH","XVGETH","NAVBNB","IOTXBTC","PIVXETH","BCPTETH","AGIBNB","OSTETH","CMTETH","TRXPAX","BCHABCPAX","WPRETH","IOSTETH","KMDETH","QSPBTC","SKYBNB","AMBBNB","WTCBNB","BRDETH","STORMBNB","PPTETH","BCNBNB","SCETH","XZCXRP","VETBNB","OSTBNB","BCCETH","VENBNB","ZECETH","NEOBNB","RDNBNB","DOCKBTC","YOYOBTC","SYSETH","STORMETH","ZENETH","BTSETH","ARDRBTC","LINKPAX","BCCBNB","STRATETH","RENBTC","BCHABCUSDC","XZCBNB","VETETH","PHXBTC","DNTETH","SNGLSBTC","SYSBTC","WTCETH","KEYETH","ICNETH","BRDBNB","NASBNB","USDCBNB","ICXBNB","CVCBNB","AGIETH","OSTBTC","BCNBTC","ADXBNB","NCASHBTC","ELFETH","PAXBNB","ASTBTC","BATBNB","CDTBTC","CLOAKETH","LTCUSDC","CHATETH","DCRBNB","XMRETH","REQETH","RDNETH","HSRBTC","APPCETH","QLCBTC","YOYOBNB","ENJBNB","BCPTBNB","IOSTBTC","ZILBNB","DOCKETH","IOTABNB","ENGETH","BCCUSDT","STORJETH","WABIBNB","MCOBNB","CMTBNB","LSKBNB","STORMBTC","MANAETH","TNBBTC","RLCETH","LOOMETH","WANBNB","RPXETH","TNTBTC","PAXBTC"]}