{"data":{"ETCBTC":2.9947939454,"LTCBNB":22.3381924906,"BTTUSDT":75.8938723942,"NAVBTC":6.4435106821,"DGDBTC":9.8358059299,"DLTETH":-2.4428081968,"XLMUSDT":-2.6656591242,"ARNETH":2.6095324455,"OAXBTC":-0.3463230733,"THETABTC":27.3150010899,"GRSETH":26.1643736007,"DLTBTC":-3.2984779556,"BTCUSDT":2.885675278,"NEOBNB":4.7596775506,"ADXETH":52.5426721226,"MCOBTC":6.4398008835,"USDCTUSD":0.0455101227,"WAVESTUSD":-4.2973890032,"TUSDUSDT":0.1571137767,"XLMBTC":-2.534310575,"QTUMUSDT":2.5825265483,"EDOBTC":11.5836486659,"THETABNB":27.3731087147,"LINKETH":5.9149431007,"LTCETH":21.3743850758,"TRXUSDT":3.7098072895,"XZCBTC":2.5231807409,"ARKBTC":25.5840137904,"TUSDBTC":-0.143016975,"EOSTUSD":12.6581813468,"ZRXETH":-0.2414729479,"BCHABCUSDT":7.6103484104,"GVTBTC":6.5305596355,"ETCUSDT":3.0272865069,"WAVESUSDT":-5.1498792362,"EVXBTC":-2.0406230212,"BCHABCBTC":7.9792215699,"USDCUSDT":0.2732798752,"TRXTUSD":4.7993771133,"LINKUSDT":5.4098771384,"XLMUSDC":-2.1187143333,"XRPETH":-1.0010324433,"BNBUSDC":27.5192917653,"BNBETH":27.0648433524,"PPTBTC":4.7136570752,"TUSDETH":-3.2658718127,"NULSUSDT":-1.9526867126,"RDNBTC":10.225910523,"VETETH":-0.1436688853,"ADXBTC":48.6838605539,"WTCBTC":3.4168125418,"ADABNB":1.9546550357,"BCHSVUSDT":1.5890176747,"LRCBTC":-4.6941043165,"BTCPAX":2.9147690337,"EOSBTC":11.7319092801,"PAXUSDT":0.185895101,"LUNBTC":0.6046934213,"ONTBTC":2.5515795606,"POWRBTC":10.2791866667,"BTTBNB":73.403754436,"EOSETH":11.3542676521,"ZILETH":-3.8244089113,"STRATBTC":5.3558024466,"OMGETH":1.8901178409,"ICXUSDT":12.5884605025,"LINKTUSD":4.7239292038,"NEBLBTC":9.9989898944,"TRXETH":2.4443205387,"NANOETH":-3.8245881902,"NULSBTC":-2.5059793554,"PAXTUSD":0.0252295653,"GASBTC":5.8036378751,"NXSBTC":-5.4531827108,"SALTBTC":2.9938413407,"MTLBTC":14.2338643287,"ADAUSDT":3.4155478862,"MFTETH":11.4883035038,"QTUMBTC":2.6907394942,"ETHUSDC":6.0228158792,"WANBTC":4.0714018959,"EOSUSDT":11.829401727,"VETUSDT":-0.2484475255,"EOSBNB":8.6449160477,"NEOUSDT":6.7423924865,"BCHSVBTC":2.0091718923,"KNCBTC":10.9274288244,"XLMPAX":-1.7757662509,"ZECBTC":0.9716275547,"LTCBTC":22.4064613913,"XEMETH":-3.2671837283,"ZRXBTC":-0.8495209603,"XEMBTC":-3.9776074172,"NEOTUSD":8.6886023312,"LINKBTC":5.8093710206,"BQXBTC":-0.4448951961,"ONTUSDT":3.0212480899,"LSKBTC":6.2578696302,"VIABTC":5.5378757055,"AIONBTC":4.6421314591,"IOTAUSDT":5.6383879282,"WAVESBTC":-5.4260977635,"GTOETH":21.8497772444,"GRSBTC":25.8509550716,"HOTETH":-12.2695326116,"BTGBTC":1.4615219577,"EOSUSDC":13.2343985714,"STEEMBTC":7.4855328348,"IOTABTC":5.8364254008,"MDABTC":0.1235431749,"USDCPAX":0.210390155,"LTCTUSD":22.5576644426,"DCRBTC":2.4693290457,"ETHBTC":6.8874642189,"KMDBTC":0.0988226711,"TRXXRP":3.0178198162,"LTCUSDT":21.8765098702,"POLYBTC":1.1793084384,"ICXBTC":14.5421717872,"WAVESETH":-6.0475223577,"ETHUSDT":7.1138811262,"BNBBTC":28.717958543,"QKCETH":7.0870946512,"ARNBTC":2.9371771786,"REPETH":7.3271337864,"EVXETH":-3.7868570979,"XRPPAX":0.1343525088,"BNBPAX":27.063192937,"ZENBTC":6.4040961281,"LTCUSDC":19.8179956176,"WAVESBNB":-8.4138864918,"NANOBTC":-3.2338136735,"ADATUSD":4.7254656789,"NPXSETH":4.4693680274,"HCBTC":22.8144300955,"XRPUSDT":0.2494830002,"BATBNB":3.413467665,"NASBTC":7.9019778605,"BTCUSDC":2.8561030039,"TRXBNB":1.6885164474,"XMRETH":6.3891451576,"NEOETH":5.5450662837,"BRDBTC":2.1031300683,"BNBUSDT":27.3280805086,"PIVXBTC":9.5039137549,"ICXETH":14.9109455057,"BCHSVTUSD":4.2627201166,"ADAETH":2.7813126618,"THETAETH":27.2367847665,"XRPTUSD":0.6343278559,"STORJBTC":10.6172863123,"BATBTC":6.087352274,"IOTAETH":5.0786927079,"CLOAKBTC":10.7135785908,"BATETH":5.5601473545,"SKYBTC":3.0273205763,"ENGBTC":1.4789837254,"TUSDBNB":-0.1232900608,"NEOBTC":6.5338909064,"REPBTC":7.501989845,"XLMBNB":-3.7360646822,"XMRBTC":6.6256005211,"XRPBNB":-0.6194234337,"WABIBTC":12.5094643952,"AEBTC":3.5338069958,"MODBTC":3.740003187,"ETHPAX":7.0859805876,"XLMETH":-3.2698766876,"RLCBTC":-0.407303437,"BCHABCTUSD":9.381371056,"OMGBTC":2.6907607601,"DASHBTC":5.8822225277,"XLMTUSD":-2.3497498315,"EOSPAX":7.558409687,"AMBBTC":-6.3828559971,"INSBTC":1.6815850199,"XRPUSDC":-0.4278858524,"XRPBTC":0.2483195208,"BCDBTC":0.5633075457,"WINGSBTC":3.3747052039},"startDate":"2019-02-02","endDate":"2019-02-09","numDays":7,"excludedPairs":["MCOBNB","ZILBTC","BLZBNB","SKYBNB","DOCKETH","SYSETH","NANOBNB","QLCETH","ETCBNB","NAVETH","CVCBNB","ICXBNB","BCCETH","IOSTETH","MITHBTC","QKCBTC","AIONBNB","HCETH","BCNBTC","DLTBNB","GXSETH","SNTETH","WINGSETH","XEMBNB","VIAETH","XVGBTC","BCNBNB","PHXBNB","WAVESPAX","STORMBNB","SCBTC","SUBETH","ICNETH","OSTBNB","CNDBTC","RPXBTC","BCPTBNB","IOTXETH","SNMBTC","LINKUSDC","TRXBTC","ZECETH","LOOMBNB","SKYETH","ENJBNB","ELFBTC","ICNBTC","MTLETH","BTCUSDS","SNMETH","GNTETH","TNTETH","WTCETH","SUBBTC","RVNBTC","GVTETH","CVCBTC","BTSETH","VIBEBTC","TRXPAX","POABNB","BQXETH","XVGETH","APPCBNB","POAETH","TRIGBNB","QLCBTC","RPXBNB","GOBTC","BCHSVPAX","MFTBTC","BNTETH","NEBLBNB","CNDETH","BCHABCUSDC","SCBNB","LENDBTC","APPCBTC","TNBBTC","APPCETH","XZCXRP","VENUSDT","BCCBTC","NCASHETH","NCASHBNB","BCHABCPAX","CLOAKETH","RLCETH","STORJETH","PHXETH","CMTBNB","AMBETH","ELFETH","LUNETH","BCNETH","AMBBNB","BCCBNB","LRCETH","NXSETH","INSETH","REQETH","TRXUSDC","ENGETH","CMTBTC","QSPETH","BCHSVUSDC","ONTETH","WPRETH","REPBNB","ARDRETH","VENBNB","QTUMBNB","CVCETH","ASTETH","VENETH","CHATETH","MCOETH","ETCETH","NPXSBTC","NASETH","CMTETH","DATAETH","OSTETH","STRATETH","KMDETH","STORMETH","VIBETH","GTOBNB","ENJBTC","BTSBNB","BCDETH","TNBETH","PPTETH","LINKPAX","IOTABNB","ADABTC","RCNBNB","AGIETH","KEYETH","HOTBTC","POABTC","ARDRBNB","MITHBNB","SALTETH","LSKETH","NAVBNB","GXSBTC","YOYOBNB","OAXETH","NULSETH","WANETH","MANABTC","VIABNB","BNBUSDS","RCNETH","AGIBNB","VIBEETH","POEETH","BLZETH","DENTBTC","TNTBTC","SNTBTC","HSRETH","PAXETH","FUNBTC","STORMBTC","SYSBNB","DOCKBTC","WPRBTC","DATABTC","DCRBNB","AGIBTC","PIVXETH","SNGLSBTC","VIBBTC","NASBNB","DNTETH","NULSBNB","POEBTC","KNCETH","CHATBTC","KEYBTC","BTGETH","ENJETH","WABIBNB","PHXBTC","PAXBTC","GTOBTC","WABIETH","ONTBNB","QSPBTC","RCNBTC","LTCPAX","FUNETH","TRIGBTC","BRDETH","VENBTC","RDNETH","NXSBNB","LENDETH","MANAETH","BCCUSDT","POWRBNB","RDNBNB","ADXBNB","AIONETH","DENTETH","RENBTC","SYSBTC","BCPTETH","CDTETH","WANBNB","DNTBTC","USDCBTC","PIVXBNB","RVNBNB","LSKBNB","WAVESUSDC","NEBLETH","ZENETH","MTHBTC","ZENBNB","RPXETH","POLYBNB","HSRBTC","OSTBTC","BRDBNB","ARKETH","DASHETH","LOOMETH","LOOMBTC","IOTXBTC","MFTBNB","VETBNB","BNTBTC","RLCBNB","PAXBNB","BCPTBTC","IOSTBTC","AEETH","USDCBNB","STEEMBNB","XZCBNB","ZILBNB","SNGLSETH","GOBNB","QSPBNB","MODETH","FUELETH","BTSBTC","QLCBNB","XZCETH","BTTBTC","YOYOBTC","POWRETH","QTUMETH","SCETH","AEBNB","CNDBNB","BLZBTC","TRIGETH","ARDRBTC","NCASHBTC","RENBNB","FUELBTC","WTCBNB","MDAETH","STEEMETH","VETBTC","MTHETH","YOYOETH","GNTBTC","GNTBNB","REQBTC","CDTBTC","DGDETH","EDOETH","ASTBTC"]}